sway_out/__init__.py
sway_out/applications.py
sway_out/connection.py
sway_out/layout.py
sway_out/layout_files.py
sway_out/main.py
sway_out/marks.py
sway_out/matching.py
sway_out/notifications.py
sway_out/utils.py
sway_out-0.1.0rc1.dist-info/METADATA
sway_out-0.1.0rc1.dist-info/WHEEL
sway_out-0.1.0rc1.dist-info/entry_points.txt
sway_out-0.1.0rc1.dist-info/RECORD
