Metadata-Version: 2.4
Name: sway-out
Version: 0.1.0rc1
Summary: A layout save/apply utility for the Sway window manager.
Requires-Python: <4,>=3.12
Requires-Dist: click<9.0.0,>=8.2.1
Requires-Dist: i3ipc<3.0.0,>=2.2.1
Requires-Dist: pydantic<3.0.0,>=2.11.7
Requires-Dist: pyyaml<7.0.0,>=6.0.2
